code_loader/helpers/__init__.py
code_loader/helpers/detection/__init__.py
code_loader/helpers/detection/metrics/object_detection_confusion_matrix_metric.py
code_loader/helpers/detection/metrics/od_cm_components_metric.py
code_loader/helpers/detection/utils.py
code_loader/helpers/detection/yolo/__init__.py
code_loader/helpers/detection/yolo/decoder.py
code_loader/helpers/detection/yolo/enums.py
code_loader/helpers/detection/yolo/grid.py
code_loader/helpers/detection/yolo/loss.py
code_loader/helpers/detection/yolo/pytorch_utils.py
code_loader/helpers/detection/yolo/utils.py
code_loader/helpers/instancesegmentation/__init__.py
code_loader/helpers/instancesegmentation/utils.py
code_loader/helpers/store/__init__.py
code_loader/helpers/store/metadata/.DS_Store
code_loader/helpers/store/metadata/__init__.py
code_loader/helpers/store/metadata/image.py
code_loader/helpers/visualizer/__init__.py
code_loader/helpers/visualizer/plot_functions.py
code_loader/helpers/visualizer/visualize.py
code_loader_helpers-1.0.35.dist-info/LICENSE
code_loader_helpers-1.0.35.dist-info/METADATA
code_loader_helpers-1.0.35.dist-info/WHEEL
code_loader_helpers-1.0.35.dist-info/RECORD
