Metadata-Version: 2.1
Name: code-loader.helpers
Version: 1.0.35
Summary: 
Author: dorhar
Author-email: doron.harnoy@tensorleap.ai
Requires-Python: >=3.8,<3.11
Classifier: Programming Language :: Python :: 3
Classifier: Programming Language :: Python :: 3.8
Classifier: Programming Language :: Python :: 3.9
Classifier: Programming Language :: Python :: 3.10
Requires-Dist: code-loader (>=1.0,<2.0)
Requires-Dist: matplotlib (>=3.3.4)
Requires-Dist: opencv-python (>=4.5.5,<5.0.0)
Requires-Dist: scikit-image (>=0.19.2,<0.20.0)
Requires-Dist: tensorflow (>=2.0,<3.0) ; platform_machine == "x86_64"
Requires-Dist: tensorflow-macos (>=2.5,<3.0) ; platform_machine == "arm64"
Requires-Dist: torch (>=1.4.0,<=2.1.0)
